universal_conf/__init__.py
universal_conf-0.1.0.dist-info/WHEEL
universal_conf-0.1.0.dist-info/METADATA
universal_conf-0.1.0.dist-info/RECORD
